CHANGES.txt
README.txt
bootstrap.py
buildout.cfg
setup.py
src/zope/__init__.py
src/zope.kgs.egg-info/PKG-INFO
src/zope.kgs.egg-info/SOURCES.txt
src/zope.kgs.egg-info/dependency_links.txt
src/zope.kgs.egg-info/entry_points.txt
src/zope.kgs.egg-info/namespace_packages.txt
src/zope.kgs.egg-info/not-zip-safe
src/zope.kgs.egg-info/requires.txt
src/zope.kgs.egg-info/top_level.txt
src/zope/kgs/README.txt
src/zope/kgs/__init__.py
src/zope/kgs/buildout.cfg.in
src/zope/kgs/buildout.py
src/zope/kgs/change.py
src/zope/kgs/changes_tests.py
src/zope/kgs/kgs.py
src/zope/kgs/latest.py
src/zope/kgs/link.py
src/zope/kgs/ppix.py
src/zope/kgs/release_data.dat
src/zope/kgs/site.py
src/zope/kgs/template.py
src/zope/kgs/tests.py
src/zope/kgs/version.py
src/zope/kgs/templates/index.html
src/zope/kgs/templates/intro.html
src/zope/kgs/templates/master.pt
src/zope/kgs/templates/menu.pt
src/zope/kgs/templates/VERSION/ANNOUNCEMENT.html
src/zope/kgs/templates/VERSION/CHANGES.html
src/zope/kgs/templates/VERSION/index.html
src/zope/kgs/templates/resources/bullet.gif
src/zope/kgs/templates/resources/button-on-bg.png
src/zope/kgs/templates/resources/header-bg2.png
src/zope/kgs/templates/resources/nav-off-bg.png
src/zope/kgs/templates/resources/nav-on-bg.png
src/zope/kgs/templates/resources/style.css